universal_agent_tools/__init__.py
universal_agent_tools/model_config.py
universal_agent_tools/observability.py
universal_agent_tools/code_chunking/__init__.py
universal_agent_tools/code_chunking/chunker.py
universal_agent_tools/code_chunking/file_type_detector.py
universal_agent_tools/code_chunking/generic_chunker.py
universal_agent_tools/code_chunking/json_chunker.py
universal_agent_tools/code_chunking/markdown_chunker.py
universal_agent_tools/code_chunking/python_chunker.py
universal_agent_tools/code_chunking/yaml_chunker.py
universal_agent_tools/codebase_analyzer/__init__.py
universal_agent_tools/codebase_analyzer/analyzer.py
universal_agent_tools/codebase_analyzer/ast_parser.py
universal_agent_tools/codebase_analyzer/clustering.py
universal_agent_tools/codebase_analyzer/pagerank.py
universal_agent_tools/document_generator/__init__.py
universal_agent_tools/document_generator/planner.py
universal_agent_tools/document_generator/prompts.py
universal_agent_tools/document_generator/writer.py
universal_agent_tools/github_tools/__init__.py
universal_agent_tools/github_tools/cli.py
universal_agent_tools/github_tools/repository.py
universal_agent_tools/mcp_framework/__init__.py
universal_agent_tools/mcp_framework/base_server.py
universal_agent_tools/mcp_framework/tool_decorator.py
universal_agent_tools/ollama_tools/__init__.py
universal_agent_tools/ollama_tools/mcp_loader.py
universal_agent_tools/ollama_tools/mcp_tool.py
universal_agent_tools/ollama_tools/ollama_llm.py
universal_agent_tools/ollama_tools/tool_parser.py
universal_agent_tools/patterns/__init__.py
universal_agent_tools/patterns/enrichment.py
universal_agent_tools/patterns/router.py
universal_agent_tools/patterns/scaffolding.py
universal_agent_tools/patterns/self_modifying.py
universal_agent_tools/sync_state/__init__.py
universal_agent_tools/sync_state/models.py
universal_agent_tools/sync_state/state_manager.py
universal_agent_tools/tool_registry/__init__.py
universal_agent_tools/tool_registry/models.py
universal_agent_tools-1.1.2.dist-info/METADATA
universal_agent_tools-1.1.2.dist-info/WHEEL
universal_agent_tools-1.1.2.dist-info/RECORD
