Metadata-Version: 2.4
Name: universal-agent-tools
Version: 1.1.2
Summary: Reusable tools and utilities for Universal Agent stack
Project-URL: Homepage, https://github.com/mjdevaccount/universal_agent_tools
Project-URL: Documentation, https://github.com/mjdevaccount/universal_agent_tools#readme
Project-URL: Repository, https://github.com/mjdevaccount/universal_agent_tools
Project-URL: Issues, https://github.com/mjdevaccount/universal_agent_tools/issues
Requires-Python: >=3.9
Requires-Dist: fastapi>=0.104.0
Requires-Dist: httpx>=0.25.0
Requires-Dist: langchain-core>=0.1.0
Requires-Dist: langchain-openai>=0.1.0
Requires-Dist: pydantic>=2.0.0
Requires-Dist: universal-agent-nexus>=3.1.0
Requires-Dist: uvicorn>=0.24.0
Provides-Extra: all
Requires-Dist: black>=23.0.0; extra == 'all'
Requires-Dist: mypy>=1.5.0; extra == 'all'
Requires-Dist: pygithub>=2.1.0; extra == 'all'
Requires-Dist: pytest-asyncio>=0.21.0; extra == 'all'
Requires-Dist: pytest-cov>=4.1.0; extra == 'all'
Requires-Dist: pytest>=7.4.0; extra == 'all'
Requires-Dist: qdrant-client>=1.7.0; extra == 'all'
Requires-Dist: ruff>=0.1.0; extra == 'all'
Provides-Extra: dev
Requires-Dist: black>=23.0.0; extra == 'dev'
Requires-Dist: mypy>=1.5.0; extra == 'dev'
Requires-Dist: pytest-asyncio>=0.21.0; extra == 'dev'
Requires-Dist: pytest-cov>=4.1.0; extra == 'dev'
Requires-Dist: pytest>=7.4.0; extra == 'dev'
Requires-Dist: ruff>=0.1.0; extra == 'dev'
Provides-Extra: github
Requires-Dist: pygithub>=2.1.0; extra == 'github'
Provides-Extra: qdrant
Requires-Dist: qdrant-client>=1.7.0; extra == 'qdrant'
